easycrypt/__init__.py
easycrypt-1.0.2.dist-info/METADATA
easycrypt-1.0.2.dist-info/WHEEL
easycrypt-1.0.2.dist-info/top_level.txt
easycrypt-1.0.2.dist-info/RECORD
