Metadata-Version: 2.1
Name: easycrypt
Version: 1.0.2
Summary: The easyest cryptography modle with AES
Home-page: UNKNOWN
Author: nathblade16@gmail.com
Author-email: nathblade16@gmail.com
License: UNKNOWN
Platform: UNKNOWN
Classifier: Programming Language :: Python :: 3
Classifier: License :: OSI Approved :: MIT License
Classifier: Operating System :: OS Independent
Requires-Python: >=3.6
